GelReportModels-7.8.0.data/scripts/ModelValidator
GelReportModels-7.8.0.data/scripts/conversion_tools.py
GelReportModels-7.8.0.data/scripts/migration_test_real_data_cancer.py
GelReportModels-7.8.0.data/scripts/migration_test_real_data_rd.py
protocols/__init__.py
protocols/coverage_0_1_0.py
protocols/cva_1_0_0.py
protocols/cva_1_1_0.py
protocols/cva_1_3_0.py
protocols/cva_1_3_1.py
protocols/cva_1_4_0.py
protocols/cva_1_5_0.py
protocols/cva_1_5_1.py
protocols/cva_1_5_2.py
protocols/ga4gh_3_0_0.py
protocols/ga4gh_3_1_0.py
protocols/metrics_1_0_0.py
protocols/metrics_1_0_1.py
protocols/metrics_1_1_0.py
protocols/metrics_1_2_0.py
protocols/metrics_1_2_1.py
protocols/metrics_1_2_2.py
protocols/opencb_1_2_0.py
protocols/opencb_1_3_0.py
protocols/participant_1_0_0.py
protocols/participant_1_0_1.py
protocols/participant_1_0_3.py
protocols/participant_1_1_0.py
protocols/participant_1_1_1.py
protocols/participant_1_1_2.py
protocols/participant_1_1_3.py
protocols/participant_1_2_0.py
protocols/participant_1_3_0.py
protocols/protocol.py
protocols/reports_2_1_0.py
protocols/reports_3_0_0.py
protocols/reports_4_0_0.py
protocols/reports_4_2_0.py
protocols/reports_5_0_0.py
protocols/reports_6_0_0.py
protocols/reports_6_0_1.py
protocols/reports_6_0_2.py
protocols/reports_6_1_0.py
protocols/reports_6_1_1.py
protocols/reports_6_2_0.py
protocols/system_0_1_0.py
protocols/catalog_variable_set/v7.3/FamilySelection.catalog_vs.json
protocols/catalog_variable_set/v7.3/GermlineSample.catalog_vs.json
protocols/catalog_variable_set/v7.3/Pedigree.catalog_vs.json
protocols/catalog_variable_set/v7.3/RareDiseaseInterpretationStatu.catalog_vs.json
protocols/catalog_variable_set/v7.3/Referral.catalog_vs.json
protocols/catalog_variable_set/v7.3/ReportedVsGeneticCheck.catalog_vs.json
protocols/catalog_variable_set/v7.3/TumourSample.catalog_vs.json
protocols/catalog_variable_set/v7.6/metrics/FamilySelection.catalog_vs.json
GelReportModels-7.8.0.dist-info/LICENSE
GelReportModels-7.8.0.dist-info/METADATA
GelReportModels-7.8.0.dist-info/WHEEL
GelReportModels-7.8.0.dist-info/top_level.txt
GelReportModels-7.8.0.dist-info/RECORD
