Metadata-Version: 2.1
Name: GelReportModels
Version: 7.8.0
Summary: Genomics England Bioinformatics team model definitions
Home-page: https://gelreportmodels.genomicsengland.co.uk
Author: Bioinformatics Team at Genomics England
Author-email: antonio.rueda-martin@genomicsengland.co.uk
License: Apache
Download-URL: https://github.com/genomicsengland/GelReportModels/archive/v7.8.0.tar.gz
Platform: UNKNOWN
Classifier: Development Status :: 3 - Alpha
Classifier: Intended Audience :: Healthcare Industry
Classifier: Intended Audience :: Science/Research
Classifier: Topic :: Scientific/Engineering :: Bio-Informatics
Classifier: License :: OSI Approved :: Apache Software License
Classifier: Programming Language :: Python :: 2.7
Classifier: Programming Language :: Python :: 3
Classifier: Programming Language :: Python :: 3.4
Classifier: Programming Language :: Python :: 3.5
Classifier: Programming Language :: Python :: 3.6
Requires-Dist: Sphinx (==1.6.2)
Requires-Dist: sphinx-rtd-theme (==0.2.4)
Requires-Dist: factory-boy (==2.9.2)
Requires-Dist: humanize (==0.5.1)
Requires-Dist: pyyaml (>=4.2b1)
Requires-Dist: dictdiffer
Requires-Dist: future (==0.16.0)
Requires-Dist: six
Requires-Dist: avro-python3 (==1.8.2)
